use/__init__.py
use/aspectizing.py
use/buffet.py
use/buffet_old.py
use/hash_alphabet.py
use/logutil.py
use/main.py
use/messages.py
use/pimp.py
use/pydantics.py
use/tools.py
justuse-0.7.1.dist-info/LICENSE
justuse-0.7.1.dist-info/METADATA
justuse-0.7.1.dist-info/WHEEL
justuse-0.7.1.dist-info/top_level.txt
justuse-0.7.1.dist-info/zip-safe
justuse-0.7.1.dist-info/RECORD
