Metadata-Version: 2.1
Name: justuse
Version: 0.7.1
Summary: a pure-python alternative to import
Home-page: https://github.com/amogorkon/justuse
Author: Anselm Kiefner
Author-email: justuse-pypi@anselm.kiefner.de
Maintainer: Anselm Kiefner
Maintainer-email: justuse-pypi@anselm.kiefner.de
License: MIT
Download-URL: https://github.com/amogorkon/justuse/archive/refs/heads/main.zip
Keywords: installing,packages,hot reload,auto install,aspect oriented,version checking,functional
Platform: any
Classifier: Development Status :: 4 - Beta
Classifier: Intended Audience :: Developers
Classifier: Natural Language :: English
Classifier: License :: OSI Approved :: MIT License
Classifier: Operating System :: OS Independent
Classifier: Programming Language :: Python :: 3 :: Only
Requires: beartype( >= 0.8.1)
Requires: furl(>= 2.1.2)
Requires: icontract(>= 2.5.4)
Requires: jinja2
Requires: packaging(== 21.0)
Requires: pip
Requires: pydantic(>= 1.8.2)
Requires: requests
Requires: toml
Requires: wheel
Requires-Python: >=3.8
License-File: LICENSE
Requires-Dist: beartype (>=0.8.1)
Requires-Dist: furl (>=2.1.2)
Requires-Dist: icontract (>=2.5.4)
Requires-Dist: jinja2
Requires-Dist: packaging (==21.0)
Requires-Dist: pip
Requires-Dist: pydantic (>=1.8.2)
Requires-Dist: requests
Requires-Dist: toml
Requires-Dist: wheel
Provides-Extra: test
Requires-Dist: pytest ; extra == 'test'
Requires-Dist: pytest-cov ; extra == 'test'
Requires-Dist: pytest-env ; extra == 'test'
